<?xml version="1.0" encoding="utf-8" standalone="yes"?>
<set xmlns:noNamespaceSchemaLocation="CardSet.xsd" name="Base Game" id="cb9fc49f-3383-4f46-8f30-61a1ed098867" gameId="e44b7146-44c3-47fd-8b8c-3340fbb0dfe5" gameVersion="1.0.0.0" version="1.0.0">
 <cards>
  <card id="1fdc7d3c-3732-436c-bd83-9c6cd9af898a" name="Ambush">
    <property name="Food" value="-3"/>
    <property name="Text" value="Negates Warning Call when attacking."/>
    <property name="Type" value="Trait"/>
  </card>
  <card id="c4bb710e-0b16-412f-849f-42e911df905b" name="Ambush">
    <property name="Food" value="-2"/>
    <property name="Text" value="Negates Warning Call when attacking."/>
    <property name="Type" value="Trait"/>
  </card>
  <card id="4185a9ac-f4d8-40b0-a42b-46636fa06e38" name="Ambush">
    <property name="Food" value="-1"/>
    <property name="Text" value="Negates Warning Call when attacking."/>
    <property name="Type" value="Trait"/>
  </card>
  <card id="d15ae51f-3aca-4a32-a217-d0ac8a05ab2f" name="Ambush">
    <property name="Food" value="0"/>
    <property name="Text" value="Negates Warning Call when attacking."/>
    <property name="Type" value="Trait"/>
  </card>
  <card id="842a0210-d6dd-4ffa-8de1-8a0b6aeb1f92" name="Ambush">
    <property name="Food" value="1"/>
    <property name="Text" value="Negates Warning Call when attacking."/>
    <property name="Type" value="Trait"/>
  </card>
  <card id="caa26d17-bf68-4267-b66f-eb333a437610" name="Ambush">
    <property name="Food" value="2"/>
    <property name="Text" value="Negates Warning Call when attacking."/>
    <property name="Type" value="Trait"/>
  </card>
  <card id="964f25e5-fe0f-49bb-9fcd-70fbdf2aabad" name="Ambush">
    <property name="Food" value="3"/>
    <property name="Text" value="Negates Warning Call when attacking."/>
    <property name="Type" value="Trait"/>
  </card>
  <card id="495b5ba8-9dbf-44b3-8ca5-a43f79cd546a" name="Burrowing">
    <property name="Food" value="1"/>
    <property name="Text" value="This species cannot be attacked if it has food equal to its Population."/>
    <property name="Type" value="Trait"/>
  </card>
  <card id="24715fde-36eb-410c-b79b-a38854e99309" name="Burrowing">
    <property name="Food" value="2"/>
    <property name="Text" value="This species cannot be attacked if it has food equal to its Population."/>
    <property name="Type" value="Trait"/>
  </card>
  <card id="be7a27f8-6c25-4e28-8945-8c97d7db4fba" name="Burrowing">
    <property name="Food" value="3"/>
    <property name="Text" value="This species cannot be attacked if it has food equal to its Population."/>
    <property name="Type" value="Trait"/>
  </card>
  <card id="19fb1894-2797-402b-b311-7c4d7033e7aa" name="Burrowing">
    <property name="Food" value="3"/>
    <property name="Text" value="This species cannot be attacked if it has food equal to its Population."/>
    <property name="Type" value="Trait"/>
  </card>
  <card id="a0268811-4df8-45b6-abd8-af4567d22321" name="Burrowing">
    <property name="Food" value="4"/>
    <property name="Text" value="This species cannot be attacked if it has food equal to its Population."/>
    <property name="Type" value="Trait"/>
  </card>
  <card id="29562d4e-908d-472e-81b3-b6799e14a896" name="Burrowing">
    <property name="Food" value="4"/>
    <property name="Text" value="This species cannot be attacked if it has food equal to its Population."/>
    <property name="Type" value="Trait"/>
  </card>
  <card id="8ea3a32c-8a8c-4879-85e6-9f189c209829" name="Burrowing">
    <property name="Food" value="5"/>
    <property name="Text" value="This species cannot be attacked if it has food equal to its Population."/>
    <property name="Type" value="Trait"/>
  </card>
  <card id="68e28da7-9903-470c-b6f7-fdfcd7da3f05" name="Carnivore">
    <property name="Food" value="-3"/>
    <property name="Text" value="May attack and eat other species.&#10;Can never eat Plant Food."/>
    <property name="Type" value="Trait"/>
  </card>
  <card id="a6d9030e-bdd5-4c4e-84d9-21d06e504cb1" name="Carnivore">
    <property name="Food" value="-2"/>
    <property name="Text" value="May attack and eat other species.&#10;Can never eat Plant Food."/>
    <property name="Type" value="Trait"/>
  </card>
  <card id="28c21162-33f4-4dc0-ae83-e5226920b58f" name="Carnivore">
    <property name="Food" value="-1"/>
    <property name="Text" value="May attack and eat other species.&#10;Can never eat Plant Food."/>
    <property name="Type" value="Trait"/>
  </card>
  <card id="20086e67-f5e6-45ae-ba7b-a38d4b39467c" name="Carnivore">
    <property name="Food" value="0"/>
    <property name="Text" value="May attack and eat other species.&#10;Can never eat Plant Food."/>
    <property name="Type" value="Trait"/>
  </card>
  <card id="74d4af26-7279-4917-9837-1fa868aeb543" name="Carnivore">
    <property name="Food" value="1"/>
    <property name="Text" value="May attack and eat other species.&#10;Can never eat Plant Food."/>
    <property name="Type" value="Trait"/>
  </card>
  <card id="70544d4b-7b75-45d3-b065-37e0062e25a0" name="Carnivore">
    <property name="Food" value="2"/>
    <property name="Text" value="May attack and eat other species.&#10;Can never eat Plant Food."/>
    <property name="Type" value="Trait"/>
  </card>
  <card id="d1d44ba1-7581-4a6c-859d-1c5a7bd980e3" name="Carnivore">
    <property name="Food" value="3"/>
    <property name="Text" value="May attack and eat other species.&#10;Can never eat Plant Food."/>
    <property name="Type" value="Trait"/>
  </card>
  <card id="fc7f42b7-282d-49dd-ac1f-78d98e22609e" name="Carnivore">
    <property name="Food" value="3"/>
    <property name="Text" value="May attack and eat other species.&#10;Can never eat Plant Food."/>
    <property name="Type" value="Trait"/>
  </card>
  <card id="ff27fc64-6a9d-4cb5-8bbe-adfdd7386096" name="Carnivore">
    <property name="Food" value="3"/>
    <property name="Text" value="May attack and eat other species.&#10;Can never eat Plant Food."/>
    <property name="Type" value="Trait"/>
  </card>
  <card id="4673d9cc-2ed6-45ba-8190-97db8ca5c2fb" name="Carnivore">
    <property name="Food" value="4"/>
    <property name="Text" value="May attack and eat other species.&#10;Can never eat Plant Food."/>
    <property name="Type" value="Trait"/>
  </card>
  <card id="28900b1d-9ed3-4f71-b539-643b55692a2c" name="Carnivore">
    <property name="Food" value="4"/>
    <property name="Text" value="May attack and eat other species.&#10;Can never eat Plant Food."/>
    <property name="Type" value="Trait"/>
  </card>
  <card id="7450239b-dad3-4fe2-a45b-91e91ae0538e" name="Carnivore">
    <property name="Food" value="4"/>
    <property name="Text" value="May attack and eat other species.&#10;Can never eat Plant Food."/>
    <property name="Type" value="Trait"/>
  </card>
  <card id="3229c6fc-5e65-4569-b4a6-1ff95743bc75" name="Carnivore">
    <property name="Food" value="5"/>
    <property name="Text" value="May attack and eat other species.&#10;Can never eat Plant Food."/>
    <property name="Type" value="Trait"/>
  </card>
  <card id="39ec1805-807b-4313-ad65-59083d9d17dc" name="Carnivore">
    <property name="Food" value="6"/>
    <property name="Text" value="May attack and eat other species.&#10;Can never eat Plant Food."/>
    <property name="Type" value="Trait"/>
  </card>
  <card id="0f25b3ec-b3d0-47b5-b9fb-0f5d21dc7950" name="Carnivore">
    <property name="Food" value="7"/>
    <property name="Text" value="May attack and eat other species.&#10;Can never eat Plant Food."/>
    <property name="Type" value="Trait"/>
  </card>
  <card id="2952b81a-1c3e-44c2-b7bd-295cc7139424" name="Carnivore">
    <property name="Food" value="8"/>
    <property name="Text" value="May attack and eat other species.&#10;Can never eat Plant Food."/>
    <property name="Type" value="Trait"/>
  </card>
  <card id="ab5c8cd1-513d-4202-bc5f-18273540e874" name="Carnivore">
    <property name="Food" value="9"/>
    <property name="Text" value="May attack and eat other species.&#10;Can never eat Plant Food."/>
    <property name="Type" value="Trait"/>
  </card>
  <card id="b1fb44be-5908-43c3-8c93-ec01059cf667" name="Climbing">
    <property name="Food" value="1"/>
    <property name="Text" value="A Carnivore must have Climbing to attack this species."/>
    <property name="Type" value="Trait"/>
  </card>
  <card id="5f257499-ef59-4172-b88b-db72d695d2ef" name="Climbing">
    <property name="Food" value="2"/>
    <property name="Text" value="A Carnivore must have Climbing to attack this species."/>
    <property name="Type" value="Trait"/>
  </card>
  <card id="54ce4b4c-0a0b-49f0-b9a7-241b9cf42a78" name="Climbing">
    <property name="Food" value="3"/>
    <property name="Text" value="A Carnivore must have Climbing to attack this species."/>
    <property name="Type" value="Trait"/>
  </card>
  <card id="a6ae1aac-40f9-4461-9a53-909fe5641b9d" name="Climbing">
    <property name="Food" value="3"/>
    <property name="Text" value="A Carnivore must have Climbing to attack this species."/>
    <property name="Type" value="Trait"/>
  </card>
  <card id="b9aaa83d-c87b-4e34-ab0f-306152129ee1" name="Climbing">
    <property name="Food" value="4"/>
    <property name="Text" value="A Carnivore must have Climbing to attack this species."/>
    <property name="Type" value="Trait"/>
  </card>
  <card id="dd098bfa-1d6a-4118-ab57-694d2fffaf0e" name="Climbing">
    <property name="Food" value="4"/>
    <property name="Text" value="A Carnivore must have Climbing to attack this species."/>
    <property name="Type" value="Trait"/>
  </card>
  <card id="8a24c024-3023-48b5-924e-0ecd2da589e3" name="Climbing">
    <property name="Food" value="5"/>
    <property name="Text" value="A Carnivore must have Climbing to attack this species."/>
    <property name="Type" value="Trait"/>
  </card>
  <card id="23e668b4-d122-4327-af3a-8e28c206c2b1" name="Cooperation">
    <property name="Food" value=""/>
    <property name="Text" value=""/>
    <property name="Type" value="Trait"/>
  </card>
  <card id="c14dffd9-ca9c-4069-b74b-d50530b2bbf0" name="Cooperation">
    <property name="Food" value=""/>
    <property name="Text" value=""/>
    <property name="Type" value="Trait"/>
  </card>
  <card id="c8726907-02cc-4b14-bfc4-8dfc5ff162d4" name="Cooperation">
    <property name="Food" value=""/>
    <property name="Text" value=""/>
    <property name="Type" value="Trait"/>
  </card>
  <card id="1fa94e36-47a3-498a-a2c0-a425e7b58da4" name="Cooperation">
    <property name="Food" value=""/>
    <property name="Text" value=""/>
    <property name="Type" value="Trait"/>
  </card>
  <card id="c2eb59e5-40e9-40d7-96c4-b22690fa43cb" name="Cooperation">
    <property name="Food" value=""/>
    <property name="Text" value=""/>
    <property name="Type" value="Trait"/>
  </card>
  <card id="b13f9653-5aa3-44f1-8d44-5150c7478c10" name="Cooperation">
    <property name="Food" value=""/>
    <property name="Text" value=""/>
    <property name="Type" value="Trait"/>
  </card>
  <card id="ae24077e-5fc9-46e9-ba9f-4b9c3ddee7ef" name="Cooperation">
    <property name="Food" value=""/>
    <property name="Text" value=""/>
    <property name="Type" value="Trait"/>
  </card>
 </cards>
</set>
